Metadata-Version: 1.0
Name: astatsa
Version: 1.0.1
Summary:  Some very basic statistical operators. 
Home-page: http://github.com/AndreaCensi/astatsa
Author: Andrea Censi
Author-email: andrea@cds.caltech.edu
License: LGPL
Download-URL: http://github.com/AndreaCensi/astatsa/tarball/1.0.1
Keywords: statistics
Platform: UNKNOWN
Classifier: Development Status :: 4 - Beta
